Topsis/__init__.py
Topsis/__main__.py
Topsis_Manan_101903311-1.0.2.dist-info/LICENSE
Topsis_Manan_101903311-1.0.2.dist-info/METADATA
Topsis_Manan_101903311-1.0.2.dist-info/WHEEL
Topsis_Manan_101903311-1.0.2.dist-info/entry_points.txt
Topsis_Manan_101903311-1.0.2.dist-info/top_level.txt
Topsis_Manan_101903311-1.0.2.dist-info/RECORD
