Metadata-Version: 2.1
Name: Topsis-Manan-101903311
Version: 1.0.2
Summary: Calculates the Topsis Score and Rank
Author: Manan Ghai
Author-email: try@gmail.com
License: MIT
Platform: UNKNOWN
Classifier: License :: OSI Approved :: MIT License
Classifier: Programming Language :: Python :: 3.6
Classifier: Programming Language :: Python :: 3.7
Classifier: Programming Language :: Python :: 3.8
License-File: LICENSE
Requires-Dist: numpy
Requires-Dist: pandas
